shuffle_sdk/__init__.py
shuffle_sdk/autocorrect_test.py
shuffle_sdk/recurse_test.py
shuffle_sdk/shuffle_sdk.py
shuffle_sdk-0.0.31.dist-info/licenses/LICENSE
shuffle_sdk-0.0.31.dist-info/METADATA
shuffle_sdk-0.0.31.dist-info/WHEEL
shuffle_sdk-0.0.31.dist-info/top_level.txt
shuffle_sdk-0.0.31.dist-info/RECORD
