Metadata-Version: 2.4
Name: shuffle_sdk
Version: 0.0.31
Summary: The SDK used for Shuffle
Home-page: https://github.com/shuffle/shuffle
Author: Fredrik Saito Odegaardstuen
Author-email: frikky@shuffler.io
License: MIT
Classifier: Programming Language :: Python :: 3
Classifier: License :: OSI Approved :: MIT License
Classifier: Operating System :: OS Independent
Requires-Python: >=3.7
License-File: LICENSE
Requires-Dist: urllib3==2.3.0
Requires-Dist: requests==2.32.3
Requires-Dist: MarkupSafe==3.0.2
Requires-Dist: liquidpy==0.8.2
Requires-Dist: flask[async]==3.1.0
Requires-Dist: waitress==3.0.2
Requires-Dist: python-dateutil==2.9.0.post0
Requires-Dist: PyJWT==2.10.1
Requires-Dist: shufflepy==0.1.8
Dynamic: author
Dynamic: author-email
Dynamic: classifier
Dynamic: description
Dynamic: description-content-type
Dynamic: home-page
Dynamic: license
Dynamic: license-file
Dynamic: requires-dist
Dynamic: requires-python
Dynamic: summary
